README.txt
plone-3.3.x.cfg
setup.cfg
setup.py
docs/CHANGES.txt
docs/INSTALL.txt
docs/LICENSE.GPL
docs/LICENSE.txt
src/slc/__init__.py
src/slc.calendarfetcher.egg-info/PKG-INFO
src/slc.calendarfetcher.egg-info/SOURCES.txt
src/slc.calendarfetcher.egg-info/dependency_links.txt
src/slc.calendarfetcher.egg-info/entry_points.txt
src/slc.calendarfetcher.egg-info/namespace_packages.txt
src/slc.calendarfetcher.egg-info/not-zip-safe
src/slc.calendarfetcher.egg-info/paster_plugins.txt
src/slc.calendarfetcher.egg-info/requires.txt
src/slc.calendarfetcher.egg-info/top_level.txt
src/slc/calendarfetcher/__init__.py
src/slc/calendarfetcher/configure.zcml
src/slc/calendarfetcher/tests.py
src/slc/calendarfetcher/utils.py
src/slc/calendarfetcher/validators.py
src/slc/calendarfetcher/browser/__init__.py
src/slc/calendarfetcher/browser/adapter.py
src/slc/calendarfetcher/browser/calendarfetcher.py
src/slc/calendarfetcher/browser/configure.zcml
src/slc/calendarfetcher/browser/interfaces.py
src/slc/calendarfetcher/browser/templates/configform.pt
src/slc/calendarfetcher/locales/slc.calendarfetcher.pot
src/slc/calendarfetcher/locales/af/LC_MESSAGES/slc.calendarfetcher.po
src/slc/calendarfetcher/locales/de/LC_MESSAGES/slc.calendarfetcher.po
src/slc/calendarfetcher/locales/en/LC_MESSAGES/slc.calendarfetcher.po
src/slc/calendarfetcher/locales/nl/LC_MESSAGES/slc.calendarfetcher.po
src/slc/calendarfetcher/profiles/default/actions.xml
src/slc/calendarfetcher/profiles/default/browserlayer.xml
src/slc/calendarfetcher/profiles/default/metadata.xml