Metadata-Version: 1.0
Name: slc.calendarfetcher
Version: 0.1b5
Summary: slc.calendarfetcher will fetch and import calendars from the ICS URLs you give it.
Home-page: http://svn.plone.org/svn/collective/
Author: JC Brand (Syslab.com GmbH)
Author-email: brand@syslab.com
License: GPL
Keywords: calendar import ical
Platform: UNKNOWN
Classifier: Framework :: Plone
Classifier: Programming Language :: Python
